{
  "project_info": {
    "project_number": "144111573765",
    "project_id": "software-development-c03f7",
    "storage_bucket": "software-development-c03f7.appspot.com"
  },
  "client": [
    {
      "client_info": {
        "mobilesdk_app_id": "1:144111573765:android:d03e55defdbd911dfa756c",
        "android_client_info": {
          "package_name": "com.reziamedia.fyrepay"
        }
      },
      "oauth_client": [
        {
          "client_id": "144111573765-9ti3nfb6utl33l74190ha1t7ntbgffv6.apps.googleusercontent.com",
          "client_type": 3
        }
      ],
      "api_key": [
        {
          "current_key": "AIzaSyDgW-8ZmzNlQnCdN3RTmPrAQo-4ztoWMj4"
        }
      ],
      "services": {
        "appinvite_service": {
          "other_platform_oauth_client": [
            {
              "client_id": "144111573765-9ti3nfb6utl33l74190ha1t7ntbgffv6.apps.googleusercontent.com",
              "client_type": 3
            }
          ]
        }
      }
    }
  ],
  "configuration_version": "1"
}